{
  "_format": "hh-sol-cache-2",
  "files": {
    "C:\\Users\\rajam\\OneDrive\\Desktop\\FYP\\contracts\\Admin.sol": {
      "lastModificationDate": 1684914701420,
      "contentHash": "038abed4e0755de555b88a58543c23ad",
      "sourceName": "contracts/Admin.sol",
      "solcConfig": {
        "version": "0.8.9",
        "settings": {
          "optimizer": {
            "enabled": false,
            "runs": 200
          },
          "outputSelection": {
            "*": {
              "*": [
                "abi",
                "evm.bytecode",
                "evm.deployedBytecode",
                "evm.methodIdentifiers",
                "metadata"
              ],
              "": [
                "ast"
              ]
            }
          }
        }
      },
      "imports": [],
      "versionPragmas": [
        "^0.8.9"
      ],
      "artifacts": [
        "Admin"
      ]
    },
    "C:\\Users\\rajam\\OneDrive\\Desktop\\FYP\\contracts\\AdminInterface.sol": {
      "lastModificationDate": 1684914701353,
      "contentHash": "c4bf55609ca0a4ca13ce0cce8330255a",
      "sourceName": "contracts/AdminInterface.sol",
      "solcConfig": {
        "version": "0.8.9",
        "settings": {
          "optimizer": {
            "enabled": false,
            "runs": 200
          },
          "outputSelection": {
            "*": {
              "*": [
                "abi",
                "evm.bytecode",
                "evm.deployedBytecode",
                "evm.methodIdentifiers",
                "metadata"
              ],
              "": [
                "ast"
              ]
            }
          }
        }
      },
      "imports": [],
      "versionPragmas": [
        "^0.8.9"
      ],
      "artifacts": [
        "Admin1"
      ]
    },
    "C:\\Users\\rajam\\OneDrive\\Desktop\\FYP\\contracts\\UpdateStudent.sol": {
      "lastModificationDate": 1684914700576,
      "contentHash": "51c031f236c49177c7537a8834a46080",
      "sourceName": "contracts/UpdateStudent.sol",
      "solcConfig": {
        "version": "0.8.9",
        "settings": {
          "optimizer": {
            "enabled": false,
            "runs": 200
          },
          "outputSelection": {
            "*": {
              "*": [
                "abi",
                "evm.bytecode",
                "evm.deployedBytecode",
                "evm.methodIdentifiers",
                "metadata"
              ],
              "": [
                "ast"
              ]
            }
          }
        }
      },
      "imports": [
        "./StudentInterface.sol",
        "./AdminInterface.sol",
        "./ConnectAdmin.sol",
        "./RegisterStudentInterface.sol",
        "./ConnectRegisterStudent.sol",
        "./RequestUpdateInterface.sol",
        "./ConnectRequestUpdate.sol",
        "./StudentHistoryInterface.sol",
        "./ConnectStudentHistory.sol"
      ],
      "versionPragmas": [
        "^0.8.9"
      ],
      "artifacts": [
        "UpdateStudent"
      ]
    },
    "C:\\Users\\rajam\\OneDrive\\Desktop\\FYP\\contracts\\StudentInterface.sol": {
      "lastModificationDate": 1684914700405,
      "contentHash": "09cd6039e96d26954a428315405b4eb7",
      "sourceName": "contracts/StudentInterface.sol",
      "solcConfig": {
        "version": "0.8.9",
        "settings": {
          "optimizer": {
            "enabled": false,
            "runs": 200
          },
          "outputSelection": {
            "*": {
              "*": [
                "abi",
                "evm.bytecode",
                "evm.deployedBytecode",
                "evm.methodIdentifiers",
                "metadata"
              ],
              "": [
                "ast"
              ]
            }
          }
        }
      },
      "imports": [],
      "versionPragmas": [
        "^0.8.9"
      ],
      "artifacts": []
    },
    "C:\\Users\\rajam\\OneDrive\\Desktop\\FYP\\contracts\\ConnectAdmin.sol": {
      "lastModificationDate": 1684914701258,
      "contentHash": "88c083aae3fbdd43fe2ffb9151778624",
      "sourceName": "contracts/ConnectAdmin.sol",
      "solcConfig": {
        "version": "0.8.9",
        "settings": {
          "optimizer": {
            "enabled": false,
            "runs": 200
          },
          "outputSelection": {
            "*": {
              "*": [
                "abi",
                "evm.bytecode",
                "evm.deployedBytecode",
                "evm.methodIdentifiers",
                "metadata"
              ],
              "": [
                "ast"
              ]
            }
          }
        }
      },
      "imports": [],
      "versionPragmas": [
        "^0.8.9"
      ],
      "artifacts": [
        "connectAdmin"
      ]
    },
    "C:\\Users\\rajam\\OneDrive\\Desktop\\FYP\\contracts\\RegisterStudentInterface.sol": {
      "lastModificationDate": 1684914700756,
      "contentHash": "025e0fa769f3523204e9836b9aca6bdb",
      "sourceName": "contracts/RegisterStudentInterface.sol",
      "solcConfig": {
        "version": "0.8.9",
        "settings": {
          "optimizer": {
            "enabled": false,
            "runs": 200
          },
          "outputSelection": {
            "*": {
              "*": [
                "abi",
                "evm.bytecode",
                "evm.deployedBytecode",
                "evm.methodIdentifiers",
                "metadata"
              ],
              "": [
                "ast"
              ]
            }
          }
        }
      },
      "imports": [
        "./StudentInterface.sol"
      ],
      "versionPragmas": [
        "^0.8.9"
      ],
      "artifacts": [
        "RegisterStudent1"
      ]
    },
    "C:\\Users\\rajam\\OneDrive\\Desktop\\FYP\\contracts\\ConnectRegisterStudent.sol": {
      "lastModificationDate": 1684914701292,
      "contentHash": "00eb026a6aa016f2e45ce594b57b1f08",
      "sourceName": "contracts/ConnectRegisterStudent.sol",
      "solcConfig": {
        "version": "0.8.9",
        "settings": {
          "optimizer": {
            "enabled": false,
            "runs": 200
          },
          "outputSelection": {
            "*": {
              "*": [
                "abi",
                "evm.bytecode",
                "evm.deployedBytecode",
                "evm.methodIdentifiers",
                "metadata"
              ],
              "": [
                "ast"
              ]
            }
          }
        }
      },
      "imports": [],
      "versionPragmas": [
        "^0.8.9"
      ],
      "artifacts": [
        "connectRegisterStudent"
      ]
    },
    "C:\\Users\\rajam\\OneDrive\\Desktop\\FYP\\contracts\\RequestUpdateInterface.sol": {
      "lastModificationDate": 1684914700719,
      "contentHash": "112c1dafea850fbedf0e2cb776b25e46",
      "sourceName": "contracts/RequestUpdateInterface.sol",
      "solcConfig": {
        "version": "0.8.9",
        "settings": {
          "optimizer": {
            "enabled": false,
            "runs": 200
          },
          "outputSelection": {
            "*": {
              "*": [
                "abi",
                "evm.bytecode",
                "evm.deployedBytecode",
                "evm.methodIdentifiers",
                "metadata"
              ],
              "": [
                "ast"
              ]
            }
          }
        }
      },
      "imports": [
        "./StudentInterface.sol"
      ],
      "versionPragmas": [
        "^0.8.9"
      ],
      "artifacts": [
        "RequestUpdate1"
      ]
    },
    "C:\\Users\\rajam\\OneDrive\\Desktop\\FYP\\contracts\\ConnectRequestUpdate.sol": {
      "lastModificationDate": 1684914701135,
      "contentHash": "14615c2acb7b445ecae1fef87f72dca1",
      "sourceName": "contracts/ConnectRequestUpdate.sol",
      "solcConfig": {
        "version": "0.8.9",
        "settings": {
          "optimizer": {
            "enabled": false,
            "runs": 200
          },
          "outputSelection": {
            "*": {
              "*": [
                "abi",
                "evm.bytecode",
                "evm.deployedBytecode",
                "evm.methodIdentifiers",
                "metadata"
              ],
              "": [
                "ast"
              ]
            }
          }
        }
      },
      "imports": [],
      "versionPragmas": [
        "^0.8.9"
      ],
      "artifacts": [
        "connectRequestUpdate"
      ]
    },
    "C:\\Users\\rajam\\OneDrive\\Desktop\\FYP\\contracts\\StudentHistoryInterface.sol": {
      "lastModificationDate": 1684914700438,
      "contentHash": "ed1b33b009bcb9af0aacf1e068939cb5",
      "sourceName": "contracts/StudentHistoryInterface.sol",
      "solcConfig": {
        "version": "0.8.9",
        "settings": {
          "optimizer": {
            "enabled": false,
            "runs": 200
          },
          "outputSelection": {
            "*": {
              "*": [
                "abi",
                "evm.bytecode",
                "evm.deployedBytecode",
                "evm.methodIdentifiers",
                "metadata"
              ],
              "": [
                "ast"
              ]
            }
          }
        }
      },
      "imports": [
        "./StudentInterface.sol"
      ],
      "versionPragmas": [
        "^0.8.9"
      ],
      "artifacts": [
        "History1"
      ]
    },
    "C:\\Users\\rajam\\OneDrive\\Desktop\\FYP\\contracts\\ConnectStudentHistory.sol": {
      "lastModificationDate": 1684914701036,
      "contentHash": "f121d250a176a64488811850d487a290",
      "sourceName": "contracts/ConnectStudentHistory.sol",
      "solcConfig": {
        "version": "0.8.9",
        "settings": {
          "optimizer": {
            "enabled": false,
            "runs": 200
          },
          "outputSelection": {
            "*": {
              "*": [
                "abi",
                "evm.bytecode",
                "evm.deployedBytecode",
                "evm.methodIdentifiers",
                "metadata"
              ],
              "": [
                "ast"
              ]
            }
          }
        }
      },
      "imports": [],
      "versionPragmas": [
        "^0.8.9"
      ],
      "artifacts": [
        "connectStudentHistory"
      ]
    },
    "C:\\Users\\rajam\\OneDrive\\Desktop\\FYP\\contracts\\StudentHistory.sol": {
      "lastModificationDate": 1684914700616,
      "contentHash": "92dc7f8ce875f067215c6f200bf68082",
      "sourceName": "contracts/StudentHistory.sol",
      "solcConfig": {
        "version": "0.8.9",
        "settings": {
          "optimizer": {
            "enabled": false,
            "runs": 200
          },
          "outputSelection": {
            "*": {
              "*": [
                "abi",
                "evm.bytecode",
                "evm.deployedBytecode",
                "evm.methodIdentifiers",
                "metadata"
              ],
              "": [
                "ast"
              ]
            }
          }
        }
      },
      "imports": [
        "./StudentInterface.sol",
        "./AdminInterface.sol",
        "./ConnectAdmin.sol"
      ],
      "versionPragmas": [
        "^0.8.9"
      ],
      "artifacts": [
        "StudentHistory"
      ]
    },
    "C:\\Users\\rajam\\OneDrive\\Desktop\\FYP\\contracts\\ScheduleAdmission.sol": {
      "lastModificationDate": 1684914700276,
      "contentHash": "9970bb5c4bc44aaddb2d7118c89ad768",
      "sourceName": "contracts/ScheduleAdmission.sol",
      "solcConfig": {
        "version": "0.8.9",
        "settings": {
          "optimizer": {
            "enabled": false,
            "runs": 200
          },
          "outputSelection": {
            "*": {
              "*": [
                "abi",
                "evm.bytecode",
                "evm.deployedBytecode",
                "evm.methodIdentifiers",
                "metadata"
              ],
              "": [
                "ast"
              ]
            }
          }
        }
      },
      "imports": [
        "./AdminInterface.sol",
        "./ConnectAdmin.sol"
      ],
      "versionPragmas": [
        "^0.8.9"
      ],
      "artifacts": [
        "ScheduleAdmissions"
      ]
    },
    "C:\\Users\\rajam\\OneDrive\\Desktop\\FYP\\contracts\\RegisterStudent.sol": {
      "lastModificationDate": 1685521364252,
      "contentHash": "d6b531aef229d3f04eba4a68cc20dfba",
      "sourceName": "contracts/RegisterStudent.sol",
      "solcConfig": {
        "version": "0.8.9",
        "settings": {
          "optimizer": {
            "enabled": false,
            "runs": 200
          },
          "outputSelection": {
            "*": {
              "*": [
                "abi",
                "evm.bytecode",
                "evm.deployedBytecode",
                "evm.methodIdentifiers",
                "metadata"
              ],
              "": [
                "ast"
              ]
            }
          }
        }
      },
      "imports": [
        "./AdminInterface.sol",
        "./ConnectAdmin.sol",
        "./ProgramInterface.sol",
        "./ConnectProgram.sol",
        "./StudentInterface.sol"
      ],
      "versionPragmas": [
        "^0.8.9"
      ],
      "artifacts": [
        "RegisterStudent"
      ]
    },
    "C:\\Users\\rajam\\OneDrive\\Desktop\\FYP\\contracts\\ConnectProgram.sol": {
      "lastModificationDate": 1684914701195,
      "contentHash": "f1282551a81feaeecb863f51195a735e",
      "sourceName": "contracts/ConnectProgram.sol",
      "solcConfig": {
        "version": "0.8.9",
        "settings": {
          "optimizer": {
            "enabled": false,
            "runs": 200
          },
          "outputSelection": {
            "*": {
              "*": [
                "abi",
                "evm.bytecode",
                "evm.deployedBytecode",
                "evm.methodIdentifiers",
                "metadata"
              ],
              "": [
                "ast"
              ]
            }
          }
        }
      },
      "imports": [],
      "versionPragmas": [
        "^0.8.9"
      ],
      "artifacts": [
        "connectProgram"
      ]
    },
    "C:\\Users\\rajam\\OneDrive\\Desktop\\FYP\\contracts\\ProgramInterface.sol": {
      "lastModificationDate": 1684914700893,
      "contentHash": "12cec008eed29e7e325708326b1359ac",
      "sourceName": "contracts/ProgramInterface.sol",
      "solcConfig": {
        "version": "0.8.9",
        "settings": {
          "optimizer": {
            "enabled": false,
            "runs": 200
          },
          "outputSelection": {
            "*": {
              "*": [
                "abi",
                "evm.bytecode",
                "evm.deployedBytecode",
                "evm.methodIdentifiers",
                "metadata"
              ],
              "": [
                "ast"
              ]
            }
          }
        }
      },
      "imports": [],
      "versionPragmas": [
        "^0.8.9"
      ],
      "artifacts": [
        "Program1"
      ]
    },
    "C:\\Users\\rajam\\OneDrive\\Desktop\\FYP\\contracts\\Program.sol": {
      "lastModificationDate": 1685521364237,
      "contentHash": "d4243a42c112acea900c6ab6f6fb70d0",
      "sourceName": "contracts/Program.sol",
      "solcConfig": {
        "version": "0.8.9",
        "settings": {
          "optimizer": {
            "enabled": false,
            "runs": 200
          },
          "outputSelection": {
            "*": {
              "*": [
                "abi",
                "evm.bytecode",
                "evm.deployedBytecode",
                "evm.methodIdentifiers",
                "metadata"
              ],
              "": [
                "ast"
              ]
            }
          }
        }
      },
      "imports": [
        "./AdminInterface.sol",
        "./ConnectAdmin.sol"
      ],
      "versionPragmas": [
        "^0.8.9"
      ],
      "artifacts": [
        "Program"
      ]
    },
    "C:\\Users\\rajam\\OneDrive\\Desktop\\FYP\\contracts\\RequestUpdate.sol": {
      "lastModificationDate": 1685521364252,
      "contentHash": "e03015df84959dd9b606ba05eb639079",
      "sourceName": "contracts/RequestUpdate.sol",
      "solcConfig": {
        "version": "0.8.9",
        "settings": {
          "optimizer": {
            "enabled": false,
            "runs": 200
          },
          "outputSelection": {
            "*": {
              "*": [
                "abi",
                "evm.bytecode",
                "evm.deployedBytecode",
                "evm.methodIdentifiers",
                "metadata"
              ],
              "": [
                "ast"
              ]
            }
          }
        }
      },
      "imports": [
        "./StudentInterface.sol",
        "./RegisterStudentInterface.sol",
        "./ConnectRegisterStudent.sol"
      ],
      "versionPragmas": [
        "^0.8.9"
      ],
      "artifacts": [
        "RequestUpdate"
      ]
    }
  }
}
